{
  "version": 1,
  "data": {
    "items": [
      {
        "name": "apple",
        "amount": 8,
        "meta": {
          "createdAt": "2025-08-17T19:26:30.166Z"
        }
      },
      {
        "name": "woodencane",
        "amount": 0,
        "meta": {
          "createdAt": "2025-08-18T15:47:05.891Z"
        }
      }
    ],
    "characters": [
      {
        "name": "bob",
        "amount": 5,
        "meta": {
          "createdAt": "2025-08-17T20:06:20.588Z"
        }
      },
      {
        "name": "betty",
        "amount": 4,
        "meta": {
          "createdAt": "2025-08-17T20:12:58.718Z"
        }
      }
    ],
    "locations": [],
    "storyevents": []
  }
}